yahoofinancials/__init__.py
yahoofinancials/cache.py
yahoofinancials/calcs.py
yahoofinancials/data.py
yahoofinancials/maps.py
yahoofinancials/sessions.py
yahoofinancials/utils.py
yahoofinancials/yf.py
yahoofinancials_gemma_analytics-1.23.dist-info/licenses/LICENSE
yahoofinancials_gemma_analytics-1.23.dist-info/METADATA
yahoofinancials_gemma_analytics-1.23.dist-info/WHEEL
yahoofinancials_gemma_analytics-1.23.dist-info/top_level.txt
yahoofinancials_gemma_analytics-1.23.dist-info/RECORD
